atila_vue/__init__.py
atila_vue/static/favicon.ico
atila_vue/static/favicon.svg
atila_vue/static/manifest.webmanifest
atila_vue/static/robots.txt
atila_vue/static/sw.js
atila_vue/static/atila-vue/components/dev/vuex-state.vue
atila_vue/static/atila-vue/css/bs-addendum.css
atila_vue/static/atila-vue/vue/config.js
atila_vue/static/atila-vue/vue/helpers.js
atila_vue/static/icon/1024.png
atila_vue/static/icon/128.png
atila_vue/static/icon/180.png
atila_vue/static/icon/256.png
atila_vue/static/icon/512.png
atila_vue/static/icon/64.png
atila_vue/static/sw/idb@7.js
atila_vue/static/sw/offline.html
atila_vue/static/sw/serviceworker-register.js
atila_vue/static/sw/img/rabbit.png
atila_vue/templates/atila-vue/bs5.j2
atila_vue/templates/atila-vue/html.j2
atila_vue/templates/atila-vue/vue.j2
atila_vue-0.4.0.dist-info/LICENSE
atila_vue-0.4.0.dist-info/METADATA
atila_vue-0.4.0.dist-info/WHEEL
atila_vue-0.4.0.dist-info/top_level.txt
atila_vue-0.4.0.dist-info/RECORD
