Metadata-Version: 2.1
Name: atila-vue
Version: 0.4.0
Summary: Atila Extension For VueJS 2 SFC and SSR
Home-page: https://gitlab.com/atila-ext/atila-vue
Author: Hans Roh
Author-email: hansroh@gmail.com
License: MIT
Download-URL: https://pypi.python.org/pypi/atila-vue
Platform: posix
Classifier: License :: OSI Approved :: MIT License
Classifier: Development Status :: 1 - Planning
Classifier: Environment :: Web Environment
Classifier: Topic :: Internet :: WWW/HTTP :: Dynamic Content
Classifier: Intended Audience :: Developers
Classifier: Intended Audience :: Science/Research
Classifier: Programming Language :: JavaScript
License-File: LICENSE
Requires-Dist: atila
Requires-Dist: jinja2
